dashgram/__init__.py
dashgram/client.py
dashgram/enums.py
dashgram/exceptions.py
dashgram/integrations/__init__.py
dashgram/integrations/aiogram.py
dashgram/integrations/base.py
dashgram/integrations/telebot.py
dashgram/integrations/telegram.py
dashgram/utils.py
dashgram-0.1.1.dist-info/METADATA
dashgram-0.1.1.dist-info/WHEEL
dashgram-0.1.1.dist-info/licenses/LICENSE
dashgram-0.1.1.dist-info/RECORD
