Metadata-Version: 2.4
Name: dashgram
Version: 0.1.1
Summary: A Python SDK for Dashgram
License: MIT
License-File: LICENSE
Keywords: sdk,api,client
Author: MrNereof
Author-email: mrnereof@gmail.com
Requires-Python: >=3.9
Classifier: Development Status :: 4 - Beta
Classifier: Programming Language :: Python :: 3
Classifier: License :: OSI Approved :: MIT License
Classifier: Operating System :: OS Independent
Requires-Dist: httpx (>=0.28.1)
Project-URL: Bug Tracker, https://github.com/Dashgram/sdk-python/issues
Project-URL: Homepage, https://github.com/Dashgram/sdk-python
Project-URL: Source Code, https://github.com/Dashgram/sdk-python
